{
  "layers":[
    {
      "hidden_units": 2048,
      "init": "glorot_normal",
      "activation": "sigmoid",
      "dropout": 0.25
    },{
      "hidden_units": 1024,
      "init": "glorot_normal",
      "activation": "sigmoid",
      "dropout": 0.25
    },{
      "init": "glorot_normal",
      "activation": "linear"
    }
  ],
  "compile": {
    "loss": "mse",
    "optimizer": {
      "option":"adam",
      "sgd": {
        "lr":0.003,
        "momentum": 0.9,
        "decay": 0.9,
        "nestrov": true
      },
      "adam": {
        "lr": 0.0001,
        "beta_1": 0.9,
        "beta_2": 0.999,
        "epsilon": 1e-8
      }
    }
  },
  "fitting": {
    "nb_epoch": 200,
    "batch_size": 2048,
    "verbose": 0,
    "early_stopping": {
      "option": "auc",
      "patience": 50
    }
  },
  "batch": {
    "is_use":true,
    "epsilon":2e-5,
    "mode": 0,
    "axis":-1,
    "momentum":0.9,
    "weights": null,
    "beta_init":"zero",
    "gamma_init":"one"
  },
  "enrichment_factor": {
    "ratio_list": [0.02, 0.01, 0.0015, 0.001]
  },
  "class_weight_option": "no_weight",
  "label_name_list": ["Keck_Pria_AS_Retest", "Keck_Pria_Continuous"]
}
